freva_xarray/__init__.py
freva_xarray/_detection.py
freva_xarray/_registry.py
freva_xarray/_version.py
freva_xarray/entrypoint.py
freva_xarray/utils.py
freva_xarray/backends/__init__.py
freva_xarray/backends/cloud.py
freva_xarray/backends/posix.py
freva_xarray-2512.0.14.dist-info/licenses/LICENSE
freva_xarray-2512.0.14.dist-info/METADATA
freva_xarray-2512.0.14.dist-info/WHEEL
freva_xarray-2512.0.14.dist-info/entry_points.txt
freva_xarray-2512.0.14.dist-info/top_level.txt
freva_xarray-2512.0.14.dist-info/RECORD
