Metadata-Version: 2.4
Name: freva-xarray
Version: 2512.0.14
Summary: A multi-format and multi-storage xarray engine with automatic engine detection, and ability to register new data format and uri type for climate data.
Author-email: "DKRZ, Clint" <freva@dkrz.de>
License: BSD 3-Clause License
Project-URL: Issues, https://github.com/freva-org/freva-xarray/issues
Project-URL: Source, https://github.com/freva-org/freva-xarray/
Keywords: xarray,climate,netcdf,zarr,grib,geotiff
Classifier: Development Status :: 4 - Beta
Classifier: Environment :: Console
Classifier: Intended Audience :: Developers
Classifier: Intended Audience :: Science/Research
Classifier: License :: OSI Approved :: BSD License
Classifier: Operating System :: POSIX :: Linux
Classifier: Programming Language :: Python :: 3
Requires-Python: >=3.9
License-File: LICENSE
Requires-Dist: xarray
Requires-Dist: fsspec
Requires-Dist: h5netcdf
Requires-Dist: scipy
Requires-Dist: zarr
Requires-Dist: cfgrib
Requires-Dist: eccodes
Requires-Dist: rioxarray
Requires-Dist: rasterio
Requires-Dist: netCDF4
Requires-Dist: s3fs
Requires-Dist: gcsfs
Requires-Dist: adlfs
Provides-Extra: dev
Requires-Dist: pytest; extra == "dev"
Requires-Dist: pytest-cov; extra == "dev"
Requires-Dist: mypy; extra == "dev"
Requires-Dist: black; extra == "dev"
Requires-Dist: isort; extra == "dev"
Requires-Dist: flake8; extra == "dev"
Requires-Dist: codespell; extra == "dev"
Dynamic: license-file
